simply_sqlite/__init__.py
simply_sqlite-0.1.141.dist-info/LICENSE
simply_sqlite-0.1.141.dist-info/METADATA
simply_sqlite-0.1.141.dist-info/WHEEL
simply_sqlite-0.1.141.dist-info/top_level.txt
simply_sqlite-0.1.141.dist-info/RECORD
