Metadata-Version: 2.1
Name: simply-sqlite
Version: 0.1.141
Summary: A simplified version of SQLite3
Home-page: UNKNOWN
Author: Oscar Gutierrez
Author-email: pyro.elidas@gmail.com
License: GNU GPLv3
Keywords: SQLite Database
Platform: UNKNOWN
Classifier: Development Status :: 4 - Beta
Classifier: Intended Audience :: Developers
Classifier: Topic :: Database
Classifier: License :: OSI Approved :: GNU General Public License v3 (GPLv3)
Classifier: Programming Language :: Python :: 3
Classifier: Operating System :: OS Independent
